dataintegrator/DataIntegrator.py
dataintegrator/__init__.py
dataintegrator-0.1.0.dist-info/LICENSE
dataintegrator-0.1.0.dist-info/METADATA
dataintegrator-0.1.0.dist-info/WHEEL
dataintegrator-0.1.0.dist-info/top_level.txt
dataintegrator-0.1.0.dist-info/RECORD
