Metadata-Version: 2.1
Name: dataintegrator
Version: 0.1.0
Summary: Python data processing and formatting tools for gwas summary stats
Home-page: https://github.com/chenyyxx/DataIntegration
Author: Yuxiang Chen
Author-email: ychen1@hsph.harvard.edu
License: MIT
Keywords: Data Integrator
Platform: UNKNOWN
Classifier: Development Status :: 5 - Production/Stable
Classifier: Intended Audience :: Science/Research
Classifier: Operating System :: MacOS
Classifier: License :: OSI Approved :: MIT License
Classifier: Programming Language :: Python :: 3
License-File: LICENSE
Requires-Dist: pyBigWig
Requires-Dist: pyliftover
Requires-Dist: numpy
Requires-Dist: pandas (>=1.0.0)
